{"cables":[{"cable_id":1187,"name":"PENBAL-5","id":"penbal-5"},{"cable_id":1208,"name":"Sweden-Finland Link (SFL)","id":"sweden-finland-link-sfl"},{"cable_id":1251,"name":"Estepona-Tetouan","id":"estepona-tetouan"},{"cable_id":1268,"name":"Finland-Estonia 3 (EESF-3)","id":"finland-estonia-3-eesf-3"},{"cable_id":1270,"name":"Latvia-Sweden 1 (LV-SE 1)","id":"latvia-sweden-1-lv-se-1"},{"cable_id":1271,"name":"Botnia","id":"botnia"},{"cable_id":1286,"name":"Italy-Croatia","id":"italy-croatia"},{"cable_id":1303,"name":"Aphrodite 2","id":"aphrodite-2"},{"cable_id":1304,"name":"CIOS","id":"cios"},{"cable_id":1455,"name":"HICS (Hawaii Inter-Island Cable System)","id":"hics-hawaii-inter-island-cable-system"},{"cable_id":1643,"name":"Columbus-II b","id":"columbus-ii-b"},{"cable_id":1645,"name":"Americas-I North","id":"americas-i-north"},{"cable_id":1702,"name":"Guernsey-Jersey-4","id":"guernsey-jersey-4"},{"cable_id":1703,"name":"UK-Channel Islands-7","id":"uk-channel-islands-7"},{"cable_id":1704,"name":"UK-Channel Islands-8","id":"uk-channel-islands-8"},{"cable_id":1730,"name":"Denmark-Sweden 17","id":"denmark-sweden-17"},{"cable_id":1737,"name":"CANTAT-3","id":"cantat-3"},{"cable_id":1765,"name":"IP-Only Denmark-Sweden","id":"ip-only-denmark-sweden"}],"rfs":"1994"}
