{"landing_points":[{"latlon":"1.389071,103.987042","url":"#/landing-point/changi-north-singapore","name":"Changi North, Singapore","id":"changi-north-singapore","landing_point_id":5940},{"latlon":"-0.067080,109.183231","url":"#/landing-point/sungai-kakap-indonesia","name":"Sungai Kakap, Indonesia","id":"sungai-kakap-indonesia","landing_point_id":9094},{"latlon":"1.173154,104.133135","url":"#/landing-point/tanjung-bemban-indonesia","name":"Tanjung Bemban, Indonesia","id":"tanjung-bemban-indonesia","landing_point_id":9096},{"latlon":"-5.981433,107.120927","url":"#/landing-point/tanjung-pakis-indonesia","name":"Tanjung Pakis, Indonesia","id":"tanjung-pakis-indonesia","landing_point_id":9095}],"length":"1,330 km","rfs":"November 2009","cable_id":1597,"owners":"PT Indonesia Satellite Corp.","notes":null,"url":"http://www.indosat.com","name":"JAKABARE","id":"jakabare"}
