{"landing_points":[{"latlon":"23.679393,58.004349","url":"#/landing-point/barka-oman","name":"Barka, Oman","id":"barka-oman","landing_point_id":8947},{"latlon":"25.616990,56.258061","url":"#/landing-point/diba-oman","name":"Diba, Oman","id":"diba-oman","landing_point_id":10579},{"latlon":"25.681247,57.797415","url":"#/landing-point/jask-iran","name":"Jask, Iran","id":"jask-iran","landing_point_id":6031},{"latlon":"26.181345,56.246830","url":"#/landing-point/khasab-oman","name":"Khasab, Oman","id":"khasab-oman","landing_point_id":7645}],"length":"600 km","rfs":"Q1 2013","cable_id":1695,"owners":"Omantel,  Vodafone","notes":null,"url":"http://www.omantel.om","name":"OMRAN/EPEG Cable System","id":"omranepeg-cable-system"}
